weco_datascience/README.md
weco_datascience/__init__.py
weco_datascience/aws.py
weco_datascience/batching.py
weco_datascience/credentials.py
weco_datascience/http.py
weco_datascience/image.py
weco_datascience/logging.py
weco_datascience/reporting.py
weco_datascience/api/__init__.py
weco_datascience/api/catalogue.py
weco_datascience/api/image.py
weco_datascience/api/snapshot.py
weco_datascience/test/V0002882.jpg
weco_datascience/test/__init__.py
weco_datascience/test/test_http.py
weco_datascience/test/test_image.py
weco_datascience/test/api/__init__.py
weco_datascience/test/api/test_catalogue.py
weco_datascience/test/api/test_images.py
weco_datascience-0.1.10.dist-info/LICENSE.md
weco_datascience-0.1.10.dist-info/WHEEL
weco_datascience-0.1.10.dist-info/METADATA
weco_datascience-0.1.10.dist-info/RECORD
